xLSTM/__init__.py
xLSTM/block.py
xLSTM/mlstm.py
xLSTM/model.py
xLSTM/slstm.py
PyxLSTM-1.0.1.dist-info/LICENSE
PyxLSTM-1.0.1.dist-info/METADATA
PyxLSTM-1.0.1.dist-info/WHEEL
PyxLSTM-1.0.1.dist-info/top_level.txt
PyxLSTM-1.0.1.dist-info/RECORD
