Metadata-Version: 2.1
Name: PyxLSTM
Version: 1.0.1
Summary: PyxLSTM: An efficient and extensible implementation of the xLSTM architecture
Author-email: Mudit Bhargava <muditbhargava666@gmail.com>
License: MIT License
Project-URL: Homepage, https://github.com/muditbhargava66/PyxLSTM
Project-URL: Repository, https://github.com/muditbhargava66/PyxLSTM
Project-URL: Issues, https://github.com/muditbhargava66/PyxLSTM/issues
Keywords: xLSTM,LSTM,language modeling,sequence modeling
Classifier: Development Status :: 5 - Production/Stable
Classifier: Intended Audience :: Developers
Classifier: Intended Audience :: Science/Research
Classifier: License :: OSI Approved :: MIT License
Classifier: Programming Language :: Python :: 3
Classifier: Programming Language :: Python :: 3.6
Classifier: Programming Language :: Python :: 3.7
Classifier: Programming Language :: Python :: 3.8
Classifier: Programming Language :: Python :: 3.9
Classifier: Programming Language :: Python :: 3.10
Classifier: Topic :: Scientific/Engineering :: Artificial Intelligence
Requires-Python: >=3.6
License-File: LICENSE
Requires-Dist: torch >=1.10.0
Requires-Dist: numpy >=1.21.0
Requires-Dist: pyyaml >=6.0.0
